github_backup_sync.py
github_backup_sync-0.1.0.dist-info/METADATA
github_backup_sync-0.1.0.dist-info/WHEEL
github_backup_sync-0.1.0.dist-info/entry_points.txt
github_backup_sync-0.1.0.dist-info/licenses/LICENSE
github_backup_sync-0.1.0.dist-info/RECORD
