Metadata-Version: 2.4
Name: github-backup-sync
Version: 0.1.0
Summary: Mirror every GitHub repository you can access into local bare git mirrors.
Project-URL: Homepage, https://github.com/basnijholt/github-backup-sync
Author-email: Bas Nijholt <bas@nijho.lt>
License: MIT
License-File: LICENSE
Requires-Python: >=3.12
Requires-Dist: gidgethub[httpx]>=5.0.0
Requires-Dist: httpx>=0.27.0
Requires-Dist: rich>=13.7.0
Requires-Dist: typer>=0.12.3
Provides-Extra: test
Requires-Dist: coverage; extra == 'test'
Requires-Dist: pytest; extra == 'test'
Requires-Dist: pytest-cov; extra == 'test'
